setup.py
malym.egg-info/PKG-INFO
malym.egg-info/SOURCES.txt
malym.egg-info/dependency_links.txt
malym.egg-info/top_level.txt
pakiet_testowy/__init__.py
pakiet_testowy/dzialania.py